WavesSearching/WavesSearching.py
WavesSearching/__init__.py
WavesSearching/disc_waves.py
WavesSearching/discrete_funcs.py
WavesSearching/utils.py
waves_searching-1.0.1.dist-info/METADATA
waves_searching-1.0.1.dist-info/WHEEL
waves_searching-1.0.1.dist-info/top_level.txt
waves_searching-1.0.1.dist-info/RECORD
