Metadata-Version: 2.1
Name: waves-searching
Version: 1.0.1
Summary: Find dispersion relation in PDE, systems of PDE, and discrete analogs
Home-page: https://www.nsu.ru/n/
Author: A.Dzhanbekova, S.Kotov, M.Malyutin, M.Samoilov, V.Utupyina, M.Arendarenko, T.Savvateeva
Author-email: 
Project-URL: github, https://github.com/great-mathematical-workshop-2024/WavesSearching
Keywords: PDE,Continuum mechanics,computer algebra,python
Classifier: Programming Language :: Python :: 3.11
Classifier: License :: OSI Approved :: MIT License
Classifier: Operating System :: OS Independent
Requires-Python: >=3.7
Requires-Dist: sympy >=1.12
